titanic_ml_pipeline/__init__.py
titanic_ml_pipeline/main.py
titanic_ml_pipeline-0.1.6.dist-info/METADATA
titanic_ml_pipeline-0.1.6.dist-info/WHEEL
titanic_ml_pipeline-0.1.6.dist-info/entry_points.txt
titanic_ml_pipeline-0.1.6.dist-info/top_level.txt
titanic_ml_pipeline-0.1.6.dist-info/RECORD
