Metadata-Version: 2.4
Name: titanic-ml-pipeline
Version: 0.1.6
Summary: Pipeline Titanic con scikit-learn (SVD + LogisticRegression)
Author: Diego Hernandez
Requires-Python: >=3.9
Requires-Dist: pandas>=1.5
Requires-Dist: numpy>=1.23
Requires-Dist: scikit-learn>=1.2
Requires-Dist: seaborn>=0.13
Requires-Dist: joblib>=1.3
Dynamic: author
Dynamic: requires-dist
Dynamic: requires-python
Dynamic: summary
